fhir_cli/__init__.py
fhir_cli/cli.py
fhir_cli/fhir_resource.py
utils/__init__.py
utils/compact.py
utils/dotty.py
utils/number_print.py
utils/prettify_json.py
fhir_cli-0.17.0.dist-info/LICENSE
fhir_cli-0.17.0.dist-info/METADATA
fhir_cli-0.17.0.dist-info/WHEEL
fhir_cli-0.17.0.dist-info/entry_points.txt
fhir_cli-0.17.0.dist-info/top_level.txt
fhir_cli-0.17.0.dist-info/RECORD
